MANIFEST.in
setup.py
nfl_insights/LICENSE
nfl_insights/README.md
nfl_insights/__init__.py
nfl_insights/nfl_game_context.py
nfl_insights/nfl_get_data.py
nfl_insights/nfl_insights_config.py
nfl_insights/nfl_language_templates.json
nfl_insights/nfl_pbp_context_builder.py
nfl_insights/nfl_play_context.py
nfl_insights/nfl_player_analytics.py
nfl_insights/nfl_questions_generator.py
nfl_insights/nfl_statements_generator.py
nfl_insights/nfl_stats_queries.py
nfl_insights/nfl_team_analytics.py
nfl_insights.egg-info/PKG-INFO
nfl_insights.egg-info/SOURCES.txt
nfl_insights.egg-info/dependency_links.txt
nfl_insights.egg-info/not-zip-safe
nfl_insights.egg-info/requires.txt
nfl_insights.egg-info/top_level.txt
nfl_insights/queries/nfl_games_info.sql
nfl_insights/queries/nfl_pbp_stats.sql
nfl_insights/queries/nfl_players_info.sql
nfl_insights/queries/nfl_teams_info.sql
nfl_insights/queries/pbp_flat_query.sql