Metadata-Version: 1.0
Name: nfl-insights
Version: 0.2.46
Summary: Contendo.ai nfl insights package
Home-page: https://github.com/sportsight-pro/sportsight-core/tree/master/nfl_insights
Author: Yahali Sherman, contendo.ai
Author-email: yahali@contendo.ai
License: MIT
Platform: UNKNOWN
